autosink_data_elt/__init__.py
autosink_data_elt/tools.py
autosink_data_elt/dataset/autosink.py
autosink_data_elt/dataset/base.py
autosink_data_elt/log/filehandler.py
autosink_data_elt/log/utils.py
autosink_data_elt/log/template/dishwashing.py
autosink_data_elt/log/template/interaction.py
autosink_data_elt/path/autosink.py
autosink_data_elt/path/backends.py
autosink_data_elt/path/base.py
autosink_data_elt-0.2.0.dist-info/WHEEL
autosink_data_elt-0.2.0.dist-info/METADATA
autosink_data_elt-0.2.0.dist-info/RECORD
